typecasts/__init__.py
typecasts/defaults/__init__.py
typecasts/defaults/base.py
typecasts/defaults/dataclass.py
typecasts/defaults/pydantic.py
typecasts/errors.py
typecasts/identity.py
typecasts/main.py
typecasts/types.py
typecasts-0.1.9.dist-info/LICENSE
typecasts-0.1.9.dist-info/WHEEL
typecasts-0.1.9.dist-info/METADATA
typecasts-0.1.9.dist-info/RECORD
