Metadata-Version: 2.1
Name: typecasts
Version: 0.1.9
Summary: Implicit type conversions for Python
Home-page: https://github.com/python-platonic/typecasts
License: MIT
Requires-Python: >=3.7,<3.10
Classifier: Development Status :: 3 - Alpha
Classifier: Intended Audience :: Developers
Classifier: License :: OSI Approved :: MIT License
Classifier: Operating System :: OS Independent
Classifier: Programming Language :: Python :: 3
Classifier: Programming Language :: Python :: 3.7
Classifier: Programming Language :: Python :: 3.8
Classifier: Programming Language :: Python :: 3.9
Classifier: Topic :: Software Development :: Libraries :: Python Modules
Requires-Dist: backports.cached-property (>=1.0.0,<2.0.0); python_version < "3.8"
Requires-Dist: dataclasses (==0.7); python_version >= "3.6" and python_version < "3.7"
Requires-Dist: documented (>=0.1.1,<0.2.0)
Requires-Dist: generic-args (>=0.0.2,<0.0.3)
Project-URL: Repository, https://github.com/python-platonic/typecasts
